g42cloudsdkecs/__init__.py
g42cloudsdkecs/v2/__init__.py
g42cloudsdkecs/v2/ecs_async_client.py
g42cloudsdkecs/v2/ecs_client.py
g42cloudsdkecs/v2/model/__init__.py
g42cloudsdkecs/v2/model/add_server_group_member_request.py
g42cloudsdkecs/v2/model/add_server_group_member_request_body.py
g42cloudsdkecs/v2/model/add_server_group_member_response.py
g42cloudsdkecs/v2/model/associate_server_virtual_ip_option.py
g42cloudsdkecs/v2/model/associate_server_virtual_ip_request.py
g42cloudsdkecs/v2/model/associate_server_virtual_ip_request_body.py
g42cloudsdkecs/v2/model/associate_server_virtual_ip_response.py
g42cloudsdkecs/v2/model/attach_server_volume_option.py
g42cloudsdkecs/v2/model/attach_server_volume_request.py
g42cloudsdkecs/v2/model/attach_server_volume_request_body.py
g42cloudsdkecs/v2/model/attach_server_volume_response.py
g42cloudsdkecs/v2/model/batch_add_server_nic_option.py
g42cloudsdkecs/v2/model/batch_add_server_nics_request.py
g42cloudsdkecs/v2/model/batch_add_server_nics_request_body.py
g42cloudsdkecs/v2/model/batch_add_server_nics_response.py
g42cloudsdkecs/v2/model/batch_attach_sharable_volumes_option.py
g42cloudsdkecs/v2/model/batch_attach_sharable_volumes_request.py
g42cloudsdkecs/v2/model/batch_attach_sharable_volumes_request_body.py
g42cloudsdkecs/v2/model/batch_attach_sharable_volumes_response.py
g42cloudsdkecs/v2/model/batch_create_server_tags_request.py
g42cloudsdkecs/v2/model/batch_create_server_tags_request_body.py
g42cloudsdkecs/v2/model/batch_create_server_tags_response.py
g42cloudsdkecs/v2/model/batch_delete_server_nic_option.py
g42cloudsdkecs/v2/model/batch_delete_server_nics_request.py
g42cloudsdkecs/v2/model/batch_delete_server_nics_request_body.py
g42cloudsdkecs/v2/model/batch_delete_server_nics_response.py
g42cloudsdkecs/v2/model/batch_delete_server_tags_request.py
g42cloudsdkecs/v2/model/batch_delete_server_tags_request_body.py
g42cloudsdkecs/v2/model/batch_delete_server_tags_response.py
g42cloudsdkecs-0.0.10b0.dist-info/LICENSE
g42cloudsdkecs-0.0.10b0.dist-info/METADATA
g42cloudsdkecs-0.0.10b0.dist-info/WHEEL
g42cloudsdkecs-0.0.10b0.dist-info/top_level.txt
g42cloudsdkecs-0.0.10b0.dist-info/RECORD
